bytedinsightskillset/__init__.py
bytedinsightskillset-0.0.1.dist-info/METADATA
bytedinsightskillset-0.0.1.dist-info/WHEEL
bytedinsightskillset-0.0.1.dist-info/top_level.txt
bytedinsightskillset-0.0.1.dist-info/RECORD
