Metadata-Version: 2.1
Name: bytedinsightskillset
Version: 0.0.1
Summary: A simple package named bytedinsightskillset
Home-page: https://github.com/artifact/bytedinsightskillset.git
Author: artifact
Author-email: artifact@example.com
License: UNKNOWN
Platform: UNKNOWN
Classifier: Programming Language :: Python :: 3
Classifier: License :: OSI Approved :: MIT License
Classifier: Operating System :: OS Independent
